QIRT/__init__.py
QIRT/latex_drawer.py
QIRT/quantum_circuit.py
QIRT/quantum_state.py
QIRT/config/__init__.py
QIRT/config/config.py
QIRT/config/default_config.ini
QIRT/utils/__init__.py
QIRT/utils/find_nth_substring.py
QIRT/utils/float_gcd.py
QIRT/utils/ket.py
QIRT/utils/np_extension.py
QIRT-1.3.0.dist-info/LICENSE.md
QIRT-1.3.0.dist-info/METADATA
QIRT-1.3.0.dist-info/WHEEL
QIRT-1.3.0.dist-info/top_level.txt
QIRT-1.3.0.dist-info/RECORD
