Metadata-Version: 2.1
Name: QIRT
Version: 1.3.0
Summary: A quantum information research toolkit
Author-email: "HSIEH, LI-YU" <lyhsieh.lou@gmail.com>
License: MIT License
Project-URL: Documentation, https://slope86.github.io/QIRT
Project-URL: API Reference, https://slope86.github.io/QIRT/reference/
Project-URL: Repository, https://github.com/Slope86/QIRT
Project-URL: Issues, https://github.com/Slope86/QIRT/issues
Classifier: Environment :: Web Environment
Classifier: Environment :: Other Environment
Classifier: Operating System :: MacOS
Classifier: Operating System :: Microsoft :: Windows
Classifier: Operating System :: POSIX :: Linux
Classifier: Programming Language :: Python :: 3 :: Only
Classifier: Programming Language :: Python :: 3.10
Classifier: Programming Language :: Python :: 3.11
Classifier: Programming Language :: Python :: 3.12
Classifier: Framework :: Jupyter
Classifier: Topic :: Scientific/Engineering
Classifier: Topic :: Scientific/Engineering :: Physics
Classifier: Intended Audience :: Science/Research
Classifier: Intended Audience :: Developers
Classifier: License :: OSI Approved :: MIT License
Requires-Python: >=3.10
License-File: LICENSE.md
Requires-Dist: qiskit[visualization]>=1.1.0
Requires-Dist: IPython>=8.24.0
Provides-Extra: dev
Requires-Dist: pytest; extra == "dev"
Requires-Dist: mkdocs; extra == "dev"
Requires-Dist: mkdocstrings[python]; extra == "dev"
Requires-Dist: mkdocs-material; extra == "dev"
